tejaspp360.py
tejaspp360-0.1.dist-info/LICENSE
tejaspp360-0.1.dist-info/WHEEL
tejaspp360-0.1.dist-info/METADATA
tejaspp360-0.1.dist-info/RECORD
