Metadata-Version: 2.1
Name: tejaspp360
Version: 0.1
Summary: My package
Author-email: tejas <tejas9patil@gmail.com>
Classifier: License :: OSI Approved :: MIT License
